wiki2video/__init__.py
wiki2video/gradio_app.py
wiki2video/assets/doctor/pipeline_test.json
wiki2video/assets/placeholder/placeholder.mp3
wiki2video/assets/placeholder/placeholder.mp4
wiki2video/cli/__init__.py
wiki2video/cli/core_project_builder.py
wiki2video/cli/cost.py
wiki2video/cli/doctor.py
wiki2video/cli/generate.py
wiki2video/cli/init.py
wiki2video/cli/main.py
wiki2video/cli/render.py
wiki2video/cli/script.py
wiki2video/config/__init__.py
wiki2video/config/config_manager.py
wiki2video/config/config_vars.py
wiki2video/config/default_config.py
wiki2video/config/support_platform.py
wiki2video/core/__init__.py
wiki2video/core/beautify_srt.py
wiki2video/core/builder.py
wiki2video/core/concat.py
wiki2video/core/gen_cover.py
wiki2video/core/parse_script.py
wiki2video/core/path_utils.py
wiki2video/core/paths.py
wiki2video/core/pipeline.py
wiki2video/core/utils.py
wiki2video/core/worker.py
wiki2video/core/working_block.py
wiki2video/core/tests/doctor_pipeline_test.py
wiki2video/core/tests/test_concat_video.py
wiki2video/dao/working_block_dao.py
wiki2video/db/__init__.py
wiki2video/db/init_db.py
wiki2video/db/schema/working_blocks.sql
wiki2video/llm_agent/__init__.py
wiki2video/llm_agent/agents/__init__.py
wiki2video/llm_agent/agents/auto_script/__init__.py
wiki2video/llm_agent/agents/auto_script/orchestrator.py
wiki2video/llm_agent/agents/utils/script_normalizer.py
wiki2video/llm_agent/agents/utils/svg_converter.py
wiki2video/llm_agent/agents/utils/wiki_fetcher.py
wiki2video/llm_agent/agents/wiki2video/__init__.py
wiki2video/llm_agent/agents/wiki2video/wiki2video_interactive.py
wiki2video/llm_agent/mcp/__init__.py
wiki2video/llm_agent/mcp/server.py
wiki2video/llm_agent/mcp/tools/__init__.py
wiki2video/llm_agent/mcp/tools/image_search/__init__.py
wiki2video/llm_agent/mcp/tools/image_search/downloader.py
wiki2video/llm_agent/mcp/tools/image_search/search.py
wiki2video/llm_agent/mcp/tools/image_search/tool.py
wiki2video/llm_agent/utils/__init__.py
wiki2video-0.0.1a1.dist-info/licenses/LICENSE
wiki2video-0.0.1a1.dist-info/METADATA
wiki2video-0.0.1a1.dist-info/WHEEL
wiki2video-0.0.1a1.dist-info/entry_points.txt
wiki2video-0.0.1a1.dist-info/top_level.txt
wiki2video-0.0.1a1.dist-info/RECORD
