Metadata-Version: 2.4
Name: wiki2video
Version: 0.0.1a1
Summary: Wiki2Video: turn Wikipedia articles into short documentary-style videos
Author-email: NP_123 <np123greatest@gmail.com>
License: MIT
Keywords: ai,video,llm,wikipedia,cli,generative-ai
Classifier: Development Status :: 3 - Alpha
Classifier: Environment :: Console
Classifier: Intended Audience :: Developers
Classifier: License :: OSI Approved :: MIT License
Classifier: Programming Language :: Python :: 3
Classifier: Programming Language :: Python :: 3.9
Classifier: Programming Language :: Python :: 3.10
Classifier: Programming Language :: Python :: 3.11
Requires-Python: >=3.9
License-File: LICENSE
Requires-Dist: backoff<3,>=2.2
Requires-Dist: dacite<2,>=1.9
Requires-Dist: fish-audio-sdk<2,>=1.1
Requires-Dist: gradio<7,>=6.0
Requires-Dist: Jinja2<4,>=3.1
Requires-Dist: moviepy<3,>=2.2
Requires-Dist: mwclient<1,>=0.11
Requires-Dist: mwparserfromhell<1,>=0.7
Requires-Dist: numpy<3,>=1.26
Requires-Dist: opencv-python<5,>=4.12
Requires-Dist: pandas<3,>=2.3
Requires-Dist: pillow<12,>=10
Requires-Dist: pydub<1,>=0.25
Requires-Dist: PyYAML<7,>=6.0
Requires-Dist: requests<3,>=2.31
Requires-Dist: rich<15,>=13
Requires-Dist: typer<1,>=0.9
Provides-Extra: openai
Requires-Dist: openai<2,>=1.0; extra == "openai"
Provides-Extra: google
Requires-Dist: google-genai<1,>=0.5; extra == "google"
Provides-Extra: svg
Requires-Dist: CairoSVG<3,>=2.8; extra == "svg"
Dynamic: license-file
